pyrpipe/__init__.py
pyrpipe/assembly.py
pyrpipe/benchmark.py
pyrpipe/mapping.py
pyrpipe/pyrpipe_engine.py
pyrpipe/pyrpipe_session.py
pyrpipe/pyrpipe_utils.py
pyrpipe/qc.py
pyrpipe/quant.py
pyrpipe/sra.py
pyrpipe/tools.py
pyrpipe/version.py
pyrpipe/report_templates/__init__.py
pyrpipe/report_templates/head.html
pyrpipe/report_templates/simple.css
pyrpipe/report_templates/simpleDiv.html
pyrpipe-0.0.4.data/scripts/pyrpipe_diagnostic.py
pyrpipe-0.0.4.dist-info/LICENSE
pyrpipe-0.0.4.dist-info/METADATA
pyrpipe-0.0.4.dist-info/WHEEL
pyrpipe-0.0.4.dist-info/top_level.txt
pyrpipe-0.0.4.dist-info/RECORD
