Metadata-Version: 2.1
Name: pyrpipe
Version: 0.0.4
Summary: pyrpipe
Home-page: https://github.com/urmi-21/pyrpipe
Author: Urminder Singh
Author-email: usingh@iastate.edu
License: UNKNOWN
Platform: UNKNOWN
Classifier: Programming Language :: Python :: 3
Classifier: License :: OSI Approved :: MIT License
Classifier: Operating System :: Unix
Classifier: Intended Audience :: Science/Research
Classifier: Topic :: Scientific/Engineering :: Bio-Informatics
Classifier: Programming Language :: Python :: 3.6
Classifier: Programming Language :: Python :: 3.7
Requires-Python: >=3.6
Requires-Dist: dill
Requires-Dist: jinja2
Requires-Dist: weasyprint
Requires-Dist: importlib-resources
Requires-Dist: multiqc
Requires-Dist: seaborn
Requires-Dist: pyyaml
